{"v":"5.1.16","fr":25,"ip":0,"op":750,"w":1000,"h":1000,"nm":"N","ddd":0,"assets":[],"layers":[{"ddd":0,"ind":2,"ty":3,"nm":"Controller","sr":1,"ks":{"o":{"a":0,"k":0,"ix":11},"r":{"a":0,"k":0,"ix":10},"p":{"a":0,"k":[500,500,0],"ix":2},"a":{"a":0,"k":[0,0,0],"ix":1},"s":{"a":0,"k":[100,100,100],"ix":6}},"ao":0,"ef":[{"ty":5,"nm":"Gilbert Controller","np":17,"mn":"Pseudo/0vbarur0o9","ix":1,"en":1,"ef":[{"ty":6,"nm":"Animation","mn":"Pseudo/0vbarur0o9-0001","ix":1,"v":0},{"ty":0,"nm":"Start","mn":"Pseudo/0vbarur0o9-0002","ix":2,"v":{"a":1,"k":[{"i":{"x":[0.999],"y":[1]},"o":{"x":[0.75],"y":[0]},"n":["0p999_1_0p75_0"],"t":75,"s":[0],"e":[100]},{"t":95}],"ix":2}},{"ty":0,"nm":"End","mn":"Pseudo/0vbarur0o9-0003","ix":3,"v":{"a":1,"k":[{"i":{"x":[0.25],"y":[1]},"o":{"x":[0.001],"y":[0]},"n":["0p25_1_0p001_0"],"t":0,"s":[0],"e":[100]},{"t":20}],"ix":3}},{"ty":0,"nm":"Offset","mn":"Pseudo/0vbarur0o9-0004","ix":4,"v":{"a":1,"k":[{"i":{"x":[0.25],"y":[1]},"o":{"x":[0.001],"y":[0]},"n":["0p25_1_0p001_0"],"t":0,"s":[-50],"e":[0]},{"i":{"x":[0.25],"y":[1]},"o":{"x":[0.75],"y":[0]},"n":["0p25_1_0p75_0"],"t":20,"s":[0],"e":[0]},{"i":{"x":[0.999],"y":[1]},"o":{"x":[0.75],"y":[0]},"n":["0p999_1_0p75_0"],"t":75,"s":[0],"e":[50]},{"t":95}],"ix":4}},{"ty":6,"nm":"Gilbert Controller","mn":"Pseudo/0vbarur0o9-0005","ix":5,"v":0},{"ty":6,"nm":"Color","mn":"Pseudo/0vbarur0o9-0006","ix":6,"v":0},{"ty":2,"nm":"Color 1","mn":"Pseudo/0vbarur0o9-0007","ix":7,"v":{"a":0,"k":[1,0.262745098039,0.219607843137,1],"ix":7}},{"ty":2,"nm":"Color 2","mn":"Pseudo/0vbarur0o9-0008","ix":8,"v":{"a":0,"k":[1,0.419607843137,0,1],"ix":8}},{"ty":2,"nm":"Color 3","mn":"Pseudo/0vbarur0o9-0009","ix":9,"v":{"a":0,"k":[1,0.78431372549,0.262745098039,1],"ix":9}},{"ty":2,"nm":"Color 4","mn":"Pseudo/0vbarur0o9-0010","ix":10,"v":{"a":0,"k":[0.019607843137,0.807843137255,0.486274509804,1],"ix":10}},{"ty":2,"nm":"Color 5","mn":"Pseudo/0vbarur0o9-0011","ix":11,"v":{"a":0,"k":[0,0.701960784314,0.890196078431,1],"ix":11}},{"ty":2,"nm":"Color 6","mn":"Pseudo/0vbarur0o9-0012","ix":12,"v":{"a":0,"k":[0.854901960784,0.227450980392,0.701960784314,1],"ix":12}},{"ty":7,"nm":"On white background","mn":"Pseudo/0vbarur0o9-0013","ix":13,"v":{"a":0,"k":1,"ix":13}},{"ty":7,"nm":"Use only Color 1","mn":"Pseudo/0vbarur0o9-0014","ix":14,"v":{"a":0,"k":0,"ix":14}},{"ty":6,"nm":"Gilbert Controller","mn":"Pseudo/0vbarur0o9-0015","ix":15,"v":0}]}],"ip":0,"op":750,"st":0,"bm":0},{"ddd":0,"ind":3,"ty":4,"nm":"N 1","sr":1,"ks":{"o":{"a":0,"k":100,"ix":11},"r":{"a":0,"k":0,"ix":10},"p":{"a":0,"k":[500,500,0],"ix":2},"a":{"a":0,"k":[500,500,0],"ix":1},"s":{"a":0,"k":[100,100,100],"ix":6}},"ao":0,"shapes":[{"ty":"gr","it":[{"ind":0,"ty":"sh","ix":1,"ks":{"a":0,"k":{"i":[[0,0],[0,0],[-19.049,0],[0,0],[0,0],[0,-19.049],[0,0],[0,0],[19.049,0],[0,0]],"o":[[0,0],[0,19.049],[0,0],[0,0],[19.049,0],[0,0],[0,0],[0,19.049],[0,0],[0,0]],"v":[[-59.77,-306.732],[-59.77,-178.797],[-25.279,-144.305],[10.721,-144.305],[46.721,-144.305],[81.213,-109.814],[81.213,236.241],[81.213,272.241],[46.721,306.732],[-81.213,306.732]],"c":false},"ix":2},"nm":"Path 1","mn":"ADBE Vector Shape - Group","hd":false},{"ty":"st","c":{"a":0,"k":[0,0.701960802078,0.890196084976,1],"ix":3,"x":"var $bm_rt;\ntry {\n    var FM_controllerComp = thisComp;\n    var FM_controllerLayer = FM_controllerComp.layer('Controller');\n    $bm_rt = FM_controllerLayer.effect('Gilbert Controller')('Color 5');\n} catch (e) {\n    $bm_rt = value;\n}"},"o":{"a":0,"k":100,"ix":4,"x":"var $bm_rt;\ntry {\n    var FM_controllerComp = thisComp;\n    var FM_controllerLayer = FM_controllerComp.layer('Controller');\n    if (FM_controllerLayer.effect('Gilbert Controller')('Use only Color 1') == 1)\n        $bm_rt = 0;\n    else\n        $bm_rt = 100;\n} catch (e) {\n    $bm_rt = value;\n}"},"w":{"a":0,"k":72,"ix":5},"lc":1,"lj":1,"ml":10,"nm":"Stroke 1","mn":"ADBE Vector Graphic - Stroke","hd":false},{"ty":"tr","p":{"a":0,"k":[339.583,463.76],"ix":2},"a":{"a":0,"k":[0,0],"ix":1},"s":{"a":0,"k":[100,100],"ix":3},"r":{"a":0,"k":0,"ix":6},"o":{"a":0,"k":100,"ix":7},"sk":{"a":0,"k":0,"ix":4},"sa":{"a":0,"k":0,"ix":5},"nm":"Transform"}],"nm":"Group 1","np":2,"cix":2,"ix":1,"mn":"ADBE Vector Group","hd":false},{"ty":"tm","s":{"a":0,"k":0,"ix":1,"x":"var $bm_rt;\ntry {\n    var FM_controllerComp = thisComp;\n    var FM_controllerLayer = FM_controllerComp.layer('Controller');\n    $bm_rt = div(FM_controllerLayer.effect('Gilbert Controller')('Start'), 2);\n} catch (e) {\n    $bm_rt = value;\n}"},"e":{"a":0,"k":100,"ix":2,"x":"var $bm_rt;\ntry {\n    var FM_controllerComp = thisComp;\n    var FM_controllerLayer = FM_controllerComp.layer('Controller');\n    $bm_rt = div(FM_controllerLayer.effect('Gilbert Controller')('End'), 2);\n} catch (e) {\n    $bm_rt = value;\n}"},"o":{"a":0,"k":0,"ix":3,"x":"var $bm_rt;\ntry {\n    var FM_controllerComp = thisComp;\n    var FM_controllerLayer = FM_controllerComp.layer('Controller');\n    $bm_rt = linear(FM_controllerLayer.effect('Gilbert Controller')('Offset'), -50, 50, 0, 180);\n} catch (e) {\n    $bm_rt = value;\n}"},"m":1,"ix":2,"nm":"Trim Paths 1","mn":"ADBE Vector Filter - Trim","hd":false}],"ip":0,"op":750,"st":0,"bm":1},{"ddd":0,"ind":4,"ty":4,"nm":"N 2","sr":1,"ks":{"o":{"a":0,"k":100,"ix":11},"r":{"a":0,"k":0,"ix":10},"p":{"a":0,"k":[500,500,0],"ix":2},"a":{"a":0,"k":[500,500,0],"ix":1},"s":{"a":0,"k":[100,100,100],"ix":6}},"ao":0,"shapes":[{"ty":"gr","it":[{"ind":0,"ty":"sh","ix":1,"ks":{"a":0,"k":{"i":[[0,0],[0,0],[-53.269,0],[0,53.268],[0,0],[0,0],[-53.267,0],[0,-53.268],[0,0],[0,0],[-53.268,0],[0,53.268],[0,0]],"o":[[0,0],[0,53.268],[53.266,0],[0,0],[0,0],[0,-53.268],[53.269,0],[0,0],[0,0],[0,53.268],[53.267,0],[0,0],[0,0]],"v":[[-289.349,109.183],[-289.349,176.024],[-192.9,272.474],[-96.451,176.024],[-96.451,109.183],[-96.451,-176.024],[-0.001,-272.474],[96.449,-176.024],[96.449,109.183],[96.449,176.024],[192.899,272.474],[289.349,176.024],[289.349,109.183]],"c":false},"ix":2},"nm":"Path 1","mn":"ADBE Vector Shape - Group","hd":false},{"ty":"st","c":{"a":0,"k":[1,0.419607847929,0,1],"ix":3,"x":"var $bm_rt;\ntry {\n    var FM_controllerComp = thisComp;\n    var FM_controllerLayer = FM_controllerComp.layer('Controller');\n    $bm_rt = FM_controllerLayer.effect('Gilbert Controller')('Color 2');\n} catch (e) {\n    $bm_rt = value;\n}"},"o":{"a":0,"k":100,"ix":4,"x":"var $bm_rt;\ntry {\n    var FM_controllerComp = thisComp;\n    var FM_controllerLayer = FM_controllerComp.layer('Controller');\n    if (FM_controllerLayer.effect('Gilbert Controller')('Use only Color 1') == 1)\n        $bm_rt = 0;\n    else\n        $bm_rt = 100;\n} catch (e) {\n    $bm_rt = value;\n}"},"w":{"a":0,"k":72,"ix":5},"lc":1,"lj":1,"ml":10,"nm":"Stroke 1","mn":"ADBE Vector Graphic - Stroke","hd":false},{"ty":"tr","p":{"a":0,"k":[517.246,590.817],"ix":2},"a":{"a":0,"k":[0,0],"ix":1},"s":{"a":0,"k":[100,100],"ix":3},"r":{"a":0,"k":0,"ix":6},"o":{"a":0,"k":100,"ix":7},"sk":{"a":0,"k":0,"ix":4},"sa":{"a":0,"k":0,"ix":5},"nm":"Transform"}],"nm":"Group 2","np":2,"cix":2,"ix":1,"mn":"ADBE Vector Group","hd":false},{"ty":"tm","s":{"a":0,"k":0,"ix":1,"x":"var $bm_rt;\ntry {\n    var FM_controllerComp = thisComp;\n    var FM_controllerLayer = FM_controllerComp.layer('Controller');\n    $bm_rt = div(FM_controllerLayer.effect('Gilbert Controller')('Start'), 2);\n} catch (e) {\n    $bm_rt = value;\n}"},"e":{"a":0,"k":100,"ix":2,"x":"var $bm_rt;\ntry {\n    var FM_controllerComp = thisComp;\n    var FM_controllerLayer = FM_controllerComp.layer('Controller');\n    $bm_rt = div(FM_controllerLayer.effect('Gilbert Controller')('End'), 2);\n} catch (e) {\n    $bm_rt = value;\n}"},"o":{"a":0,"k":0,"ix":3,"x":"var $bm_rt;\ntry {\n    var FM_controllerComp = thisComp;\n    var FM_controllerLayer = FM_controllerComp.layer('Controller');\n    $bm_rt = linear(FM_controllerLayer.effect('Gilbert Controller')('Offset'), -50, 50, 0, 180);\n} catch (e) {\n    $bm_rt = value;\n}"},"m":1,"ix":2,"nm":"Trim Paths 1","mn":"ADBE Vector Filter - Trim","hd":false}],"ip":0,"op":750,"st":0,"bm":1},{"ddd":0,"ind":5,"ty":4,"nm":"N BG","sr":1,"ks":{"o":{"a":0,"k":100,"ix":11},"r":{"a":0,"k":0,"ix":10},"p":{"a":0,"k":[500,500,0],"ix":2},"a":{"a":0,"k":[500,500,0],"ix":1},"s":{"a":0,"k":[100,100,100],"ix":6}},"ao":0,"shapes":[{"ty":"gr","it":[{"ind":0,"ty":"sh","ix":1,"ks":{"a":0,"k":{"i":[[0,0],[0,0],[-19.049,0],[0,0],[0,0],[0,-19.049],[0,0],[0,0],[19.049,0],[0,0]],"o":[[0,0],[0,19.049],[0,0],[0,0],[19.049,0],[0,0],[0,0],[0,19.049],[0,0],[0,0]],"v":[[-59.77,-306.732],[-59.77,-178.797],[-25.279,-144.305],[10.721,-144.305],[46.721,-144.305],[81.213,-109.814],[81.213,236.241],[81.213,272.241],[46.721,306.732],[-81.213,306.732]],"c":false},"ix":2},"nm":"Path 1","mn":"ADBE Vector Shape - Group","hd":false},{"ty":"tr","p":{"a":0,"k":[339.583,463.76],"ix":2},"a":{"a":0,"k":[0,0],"ix":1},"s":{"a":0,"k":[100,100],"ix":3},"r":{"a":0,"k":0,"ix":6},"o":{"a":0,"k":100,"ix":7},"sk":{"a":0,"k":0,"ix":4},"sa":{"a":0,"k":0,"ix":5},"nm":"Transform"}],"nm":"Group 1","np":1,"cix":2,"ix":1,"mn":"ADBE Vector Group","hd":false},{"ty":"gr","it":[{"ind":0,"ty":"sh","ix":1,"ks":{"a":0,"k":{"i":[[0,0],[0,0],[-53.269,0],[0,53.268],[0,0],[0,0],[-53.267,0],[0,-53.268],[0,0],[0,0],[-53.268,0],[0,53.268],[0,0]],"o":[[0,0],[0,53.268],[53.266,0],[0,0],[0,0],[0,-53.268],[53.269,0],[0,0],[0,0],[0,53.268],[53.267,0],[0,0],[0,0]],"v":[[-289.349,109.183],[-289.349,176.024],[-192.9,272.474],[-96.451,176.024],[-96.451,109.183],[-96.451,-176.024],[-0.001,-272.474],[96.449,-176.024],[96.449,109.183],[96.449,176.024],[192.899,272.474],[289.349,176.024],[289.349,109.183]],"c":false},"ix":2},"nm":"Path 1","mn":"ADBE Vector Shape - Group","hd":false},{"ty":"tr","p":{"a":0,"k":[517.246,590.817],"ix":2},"a":{"a":0,"k":[0,0],"ix":1},"s":{"a":0,"k":[100,100],"ix":3},"r":{"a":0,"k":0,"ix":6},"o":{"a":0,"k":100,"ix":7},"sk":{"a":0,"k":0,"ix":4},"sa":{"a":0,"k":0,"ix":5},"nm":"Transform"}],"nm":"Group 2","np":1,"cix":2,"ix":2,"mn":"ADBE Vector Group","hd":false},{"ty":"tm","s":{"a":0,"k":0,"ix":1,"x":"var $bm_rt;\ntry {\n    var FM_controllerComp = thisComp;\n    var FM_controllerLayer = FM_controllerComp.layer('Controller');\n    $bm_rt = div(FM_controllerLayer.effect('Gilbert Controller')('Start'), 2);\n} catch (e) {\n    $bm_rt = value;\n}"},"e":{"a":0,"k":100,"ix":2,"x":"var $bm_rt;\ntry {\n    var FM_controllerComp = thisComp;\n    var FM_controllerLayer = FM_controllerComp.layer('Controller');\n    $bm_rt = div(FM_controllerLayer.effect('Gilbert Controller')('End'), 2);\n} catch (e) {\n    $bm_rt = value;\n}"},"o":{"a":0,"k":0,"ix":3,"x":"var $bm_rt;\ntry {\n    var FM_controllerComp = thisComp;\n    var FM_controllerLayer = FM_controllerComp.layer('Controller');\n    $bm_rt = linear(FM_controllerLayer.effect('Gilbert Controller')('Offset'), -50, 50, 0, 180);\n} catch (e) {\n    $bm_rt = value;\n}"},"m":1,"ix":3,"nm":"Trim Paths 1","mn":"ADBE Vector Filter - Trim","hd":false},{"ty":"st","c":{"a":0,"k":[1,1,1,1],"ix":3,"x":"var $bm_rt;\ntry {\n    var FM_controllerComp = thisComp;\n    var FM_controllerLayer = FM_controllerComp.layer('Controller');\n    if (FM_controllerLayer.effect('Gilbert Controller')('Use only Color 1') == 1)\n        $bm_rt = FM_controllerLayer.effect('Gilbert Controller')('Color 1');\n    else\n        $bm_rt = value;\n} catch (e) {\n    $bm_rt = value;\n}"},"o":{"a":0,"k":100,"ix":4,"x":"var $bm_rt;\ntry {\n    var FM_controllerComp = thisComp;\n    var FM_controllerLayer = FM_controllerComp.layer('Controller');\n    if (FM_controllerLayer.effect('Gilbert Controller')('Use only Color 1') == 1)\n        $bm_rt = 100;\n    else\n        $bm_rt = mul(FM_controllerLayer.effect('Gilbert Controller')('On white background'), 100);\n} catch (e) {\n    $bm_rt = value;\n}"},"w":{"a":0,"k":72,"ix":5},"lc":1,"lj":1,"ml":10,"nm":"Stroke 1","mn":"ADBE Vector Graphic - Stroke","hd":false}],"ip":0,"op":750,"st":0,"bm":0}],"markers":[]}